sdk/__init__.py
sdk/admin.py
sdk/apps.py
sdk/enums.py
sdk/tests.py
sdk/utils.py
sdk/migrations/__init__.py
wlc_sdk_financeiro-1.0.0.dist-info/METADATA
wlc_sdk_financeiro-1.0.0.dist-info/WHEEL
wlc_sdk_financeiro-1.0.0.dist-info/top_level.txt
wlc_sdk_financeiro-1.0.0.dist-info/RECORD
