Metadata-Version: 2.4
Name: wlc-sdk-financeiro
Version: 1.0.0
Summary: SDK for Finance Module
Home-page: https://github.com/wlc-solucoes/wlc-sdk-financeiro.git
Author: WLC Soluções
Author-email: analiciasouza.11@gmail.com
Classifier: Environment :: Web Environment
Classifier: Framework :: Django
Classifier: Intended Audience :: Developers
Classifier: Programming Language :: Python
Requires-Dist: django
Requires-Dist: djangorestframework
Dynamic: author
Dynamic: author-email
Dynamic: classifier
Dynamic: home-page
Dynamic: requires-dist
Dynamic: summary
